<?xml version="1.0" encoding="UTF-8"?>
<databaseChangeLog
        xmlns:xsi="http://www.w3.org/2001/XMLSchema-instance"
        xmlns="http://www.liquibase.org/xml/ns/dbchangelog"
        xsi:schemaLocation="http://www.liquibase.org/xml/ns/dbchangelog http://www.liquibase.org/xml/ns/dbchangelog/dbchangelog-3.8.xsd">

    <changeSet id="2021-10-23 12:11:00" author="ksamorodov">
        <sqlFile path="1.0.1/sql/01__table_direction.sql" relativeToChangelogFile="true"/>
    </changeSet>

    <changeSet id="2021-10-23 12:12:00" author="ksamorodov">
        <sqlFile path="1.0.1/sql/02__student_group.sql" relativeToChangelogFile="true"/>
    </changeSet>

    <changeSet id="2021-10-23 12:13:00" author="ksamorodov">
        <sqlFile path="1.0.1/sql/03_table_student.sql" relativeToChangelogFile="true"/>
    </changeSet>

    <changeSet id="2021-10-23 12:46:00" author="ksamorodov">
        <sqlFile path="1.0.1/sql/04_table_institute.sql" relativeToChangelogFile="true"/>
    </changeSet>

    <changeSet id="2021-10-23 12:47:00" author="ksamorodov">
        <sqlFile path="1.0.1/sql/05_table_department.sql" relativeToChangelogFile="true"/>
    </changeSet>

</databaseChangeLog>